quotee/__init__.py
quotee/random.py
quotee-0.0.1.dist-info/LICENSE
quotee-0.0.1.dist-info/METADATA
quotee-0.0.1.dist-info/WHEEL
quotee-0.0.1.dist-info/top_level.txt
quotee-0.0.1.dist-info/RECORD
